hbb2obb/__init__.py
hbb2obb/__version__.py
hbb2obb/cli.py
hbb2obb/converter.py
hbb2obb/evaluator.py
hbb2obb/utils.py
hbb2obb-1.1.0.dist-info/licenses/LICENSE
hbb2obb-1.1.0.dist-info/METADATA
hbb2obb-1.1.0.dist-info/WHEEL
hbb2obb-1.1.0.dist-info/entry_points.txt
hbb2obb-1.1.0.dist-info/top_level.txt
hbb2obb-1.1.0.dist-info/RECORD
