Metadata-Version: 2.4
Name: hbb2obb
Version: 1.1.0
Summary: Toolkit for converting horizontal bounding boxes to oriented bounding boxes using segmentation models and evaluation of the conversion against ground truth.
Author-email: Robert Fonod <robert.fonod@ieee.org>
License: MIT License
Project-URL: Homepage, https://github.com/rfonod/hbb2obb/
Project-URL: Repository, https://github.com/rfonod/hbb2obb/
Project-URL: Changelog, https://github.com/rfonod/hbb2obb/releases
Project-URL: Issues, https://github.com/rfonod/hbb2obb/issues/
Keywords: bounding-box,oriented-bounding-box,rotated-bounding-box,horizontal-bounding-box,axis-aligned-bounding-box,object detection,segmentation,evaluation,computer-vision,aerial-imagery,drone-footage,remote-sensing,annotation-tools,label-conversion,YOLO-format,COCO-format,evaluation-metrics,iou-evaluation,hyperparameter-optimization
Classifier: Development Status :: 5 - Production/Stable
Classifier: License :: OSI Approved :: MIT License
Classifier: Operating System :: OS Independent
Classifier: Programming Language :: Python :: 3
Classifier: Programming Language :: Python :: 3.9
Classifier: Programming Language :: Python :: 3.10
Classifier: Programming Language :: Python :: 3.11
Classifier: Programming Language :: Python :: 3.12
Classifier: Programming Language :: Python :: 3.13
Classifier: Intended Audience :: Developers
Classifier: Intended Audience :: Science/Research
Classifier: Topic :: Scientific/Engineering
Classifier: Topic :: Software Development
Requires-Python: >=3.9
License-File: LICENSE
Requires-Dist: ultralytics>=8.3.237
Requires-Dist: shapely>=2.0.7
Provides-Extra: dev
Requires-Dist: pytest>=7.0.0; extra == "dev"
Requires-Dist: ruff>=0.11.0; extra == "dev"
Dynamic: license-file
